boxdiff/__init__.py
boxdiff/models/__init__.py
boxdiff/models/core.py
boxdiff/models/deltas.py
boxdiff/models/flags.py
boxdiff-0.2.0.dist-info/METADATA
boxdiff-0.2.0.dist-info/WHEEL
boxdiff-0.2.0.dist-info/RECORD
